yomu/__init__.py
yomu/readme.py
yomu-0.2.0.dist-info/LICENSE
yomu-0.2.0.dist-info/METADATA
yomu-0.2.0.dist-info/WHEEL
yomu-0.2.0.dist-info/entry_points.txt
yomu-0.2.0.dist-info/top_level.txt
yomu-0.2.0.dist-info/RECORD
