Metadata-Version: 2.1
Name: yomu
Version: 0.2.0
Summary: Generates the README for the 'How to Python Code' repo
Home-page: https://github.com/TheRenegadeCoder/how-to-python-readme
Author: The Renegade Coder
Author-email: jeremy.grifski@therenegadecoder.com
Classifier: Programming Language :: Python :: 3.9
Classifier: Programming Language :: Python :: 3.10
Classifier: Programming Language :: Python :: 3.11
Classifier: Operating System :: OS Independent
Classifier: Development Status :: 5 - Production/Stable
Classifier: License :: OSI Approved :: MIT License
License-File: LICENSE
Requires-Dist: feedparser (>=6)
Requires-Dist: beautifulsoup4 (>=4)
Requires-Dist: SnakeMD (>=2)
